hiearch/__init__.py
hiearch/graphviz_input.py
hiearch/graphviz_output.py
hiearch/hh_edge.py
hiearch/hh_node.py
hiearch/hh_view.py
hiearch/hiearch.py
hiearch/util.py
hiearch/data/styles/state_machine.yaml
hiearch/data/styles/use_case.yaml
hiearch-0.7.0.dist-info/METADATA
hiearch-0.7.0.dist-info/WHEEL
hiearch-0.7.0.dist-info/entry_points.txt
hiearch-0.7.0.dist-info/licenses/LICENSE
hiearch-0.7.0.dist-info/RECORD
