Metadata-Version: 2.4
Name: hiearch
Version: 0.7.0
Summary: Generates multi-view diagrams from textual descriptions
Project-URL: Homepage, https://github.com/asherikov/hiearch
Project-URL: Issues, https://github.com/asherikov/hiearch/issues
Author-email: Alexander Sherikov <asherikov@yandex.com>
License-File: LICENSE
Classifier: Development Status :: 4 - Beta
Classifier: License :: OSI Approved :: Apache Software License
Classifier: Operating System :: OS Independent
Classifier: Programming Language :: Python :: 3
Classifier: Topic :: Scientific/Engineering :: Visualization
Requires-Python: >=3.8
Requires-Dist: importlib-resources
Requires-Dist: pydot
Requires-Dist: pyyaml
